marshal_poetry_demo/__init__.py
marshal_poetry_demo/app.py
marshal_poetry_demo/main.py
marshal_poetry_demo-0.1.1.dist-info/METADATA
marshal_poetry_demo-0.1.1.dist-info/WHEEL
marshal_poetry_demo-0.1.1.dist-info/entry_points.txt
marshal_poetry_demo-0.1.1.dist-info/RECORD
